{"name":"工作总结","postlist":[{"title":"试用期工作总结--IOTA","slug":"shiyongqizongjie","date":"2020-01-18T16:00:00.000Z","updated":"2022-10-19T14:40:00.264Z","comments":null,"top":null,"path":"api/articles/shiyongqizongjie.json","realPath":"/2020/shiyongqizongjie/index/","excerpt":"Welcome to my blog, enter password to read.","keywords":"南山结庐,东篱先生","cover":null,"content":null,"raw":null,"categories":[{"name":"日常随笔","path":"api/categories/日常随笔.json"},{"name":"工作总结","path":"api/categories/工作总结.json"}],"tags":[{"name":"工作总结","path":"api/tags/工作总结.json"}]}]}