{"name":"以太坊","postlist":[{"title":"如何搭建以太坊私有链","slug":"create_private_blockchain","date":"2018-03-17T16:00:00.000Z","updated":"2022-10-19T14:40:00.246Z","comments":null,"top":null,"path":"api/articles/create_private_blockchain.json","realPath":"/2018/create_private_blockchain/index/","excerpt":null,"keywords":"南山结庐,东篱先生","cover":"/img/create_private_blockchain_1.png","content":null,"raw":null,"categories":[{"name":"学习记录","path":"api/categories/学习记录.json"},{"name":"区块链","path":"api/categories/区块链.json"},{"name":"以太坊","path":"api/categories/以太坊.json"}],"tags":[{"name":"学习记录","path":"api/tags/学习记录.json"},{"name":"区块链","path":"api/tags/区块链.json"},{"name":"以太坊","path":"api/tags/以太坊.json"}]},{"title":"实现一个可管理、增发、兑换、冻结等高级功能的代币","slug":"create-token2","date":"2018-03-10T09:02:22.000Z","updated":"2022-10-19T14:40:00.245Z","comments":null,"top":null,"path":"api/articles/create-token2.json","realPath":"/2018/create-token2/index/","excerpt":null,"keywords":"南山结庐,东篱先生","cover":"/img/create_adv_token.jpg","content":null,"raw":null,"categories":[{"name":"学习记录","path":"api/categories/学习记录.json"},{"name":"区块链","path":"api/categories/区块链.json"},{"name":"以太坊","path":"api/categories/以太坊.json"}],"tags":[{"name":"区块链","path":"api/tags/区块链.json"},{"name":"以太坊","path":"api/tags/以太坊.json"}]},{"title":"一步步教你创建自己的数字货币（代币）进行ICO","slug":"create_token","date":"2018-03-08T07:02:22.000Z","updated":"2022-10-19T14:40:00.246Z","comments":null,"top":null,"path":"api/articles/create_token.json","realPath":"/2018/create_token/index/","excerpt":null,"keywords":"南山结庐,东篱先生","cover":"/img/token_info.jpeg","content":null,"raw":null,"categories":[{"name":"学习记录","path":"api/categories/学习记录.json"},{"name":"区块链","path":"api/categories/区块链.json"},{"name":"以太坊","path":"api/categories/以太坊.json"}],"tags":[{"name":"区块链","path":"api/tags/区块链.json"},{"name":"以太坊","path":"api/tags/以太坊.json"}]},{"title":"一步步教你开发、部署第一个去中心化应用(Dapp) - 宠物商店","slug":"first-dapp","date":"2018-02-25T05:02:22.000Z","updated":"2022-10-19T14:40:00.249Z","comments":null,"top":null,"path":"api/articles/first-dapp.json","realPath":"/2018/first-dapp/first-dapp/","excerpt":null,"keywords":"南山结庐,东篱先生","cover":"/img/Petshop.jpg","content":null,"raw":null,"categories":[{"name":"学习记录","path":"api/categories/学习记录.json"},{"name":"区块链","path":"api/categories/区块链.json"},{"name":"以太坊","path":"api/categories/以太坊.json"}],"tags":[{"name":"以太坊","path":"api/tags/以太坊.json"}]},{"title":"以太坊客户端Geth命令用法-参数详解","slug":"geth_cmd_options","date":"2018-02-23T16:00:00.000Z","updated":"2022-10-19T14:40:00.251Z","comments":null,"top":null,"path":"api/articles/geth_cmd_options.json","realPath":"/2018/geth_cmd_options/geth-cmd-options/","excerpt":null,"keywords":"南山结庐,东篱先生","cover":null,"content":null,"raw":null,"categories":[{"name":"学习记录","path":"api/categories/学习记录.json"},{"name":"区块链","path":"api/categories/区块链.json"},{"name":"以太坊","path":"api/categories/以太坊.json"}],"tags":[{"name":"以太坊","path":"api/tags/以太坊.json"}]},{"title":"Geth 控制台使用及 Web3.js 使用实战","slug":"geth_cmd_short","date":"2018-02-25T05:02:22.000Z","updated":"2022-10-19T14:40:00.251Z","comments":null,"top":null,"path":"api/articles/geth_cmd_short.json","realPath":"/2018/geth_cmd_short/geth-cmd-short/","excerpt":null,"keywords":"南山结庐,东篱先生","cover":null,"content":null,"raw":null,"categories":[{"name":"学习记录","path":"api/categories/学习记录.json"},{"name":"区块链","path":"api/categories/区块链.json"},{"name":"以太坊","path":"api/categories/以太坊.json"}],"tags":[{"name":"以太坊","path":"api/tags/以太坊.json"}]},{"title":"如何通过以太坊智能合约来进行众筹（ICO）","slug":"ico-crowdsale","date":"2018-03-14T04:02:22.000Z","updated":"2022-10-19T14:40:00.256Z","comments":null,"top":null,"path":"api/articles/ico-crowdsale.json","realPath":"/2018/ico-crowdsale/index/","excerpt":null,"keywords":"南山结庐,东篱先生","cover":"/img/crowdsale_create.jpeg","content":null,"raw":null,"categories":[{"name":"学习记录","path":"api/categories/学习记录.json"},{"name":"区块链","path":"api/categories/区块链.json"},{"name":"以太坊","path":"api/categories/以太坊.json"}],"tags":[{"name":"以太坊","path":"api/tags/以太坊.json"}]},{"title":"智能合约开发环境搭建及Hello World合约","slug":"init-env","date":"2018-02-23T16:00:00.000Z","updated":"2022-10-19T14:40:00.257Z","comments":null,"top":null,"path":"api/articles/init-env.json","realPath":"/2018/init-env/init-env/","excerpt":null,"keywords":"南山结庐,东篱先生","cover":"/img/open_geth_eth.jpg","content":null,"raw":null,"categories":[{"name":"学习记录","path":"api/categories/学习记录.json"},{"name":"区块链","path":"api/categories/区块链.json"},{"name":"以太坊","path":"api/categories/以太坊.json"}],"tags":[{"name":"以太坊","path":"api/tags/以太坊.json"}]},{"title":"智能合约语言 Solidity 教程系列8 - Solidity API","slug":"solidity-api","date":"2018-03-15T07:40:22.000Z","updated":"2022-10-19T14:40:00.265Z","comments":null,"top":null,"path":"api/articles/solidity-api.json","realPath":"/2018/solidity-api/solidity-api/","excerpt":null,"keywords":"南山结庐,东篱先生","cover":null,"content":null,"raw":null,"categories":[{"name":"学习记录","path":"api/categories/学习记录.json"},{"name":"区块链","path":"api/categories/区块链.json"},{"name":"以太坊","path":"api/categories/以太坊.json"}],"tags":[{"name":"Solidity手册","path":"api/tags/Solidity手册.json"}]},{"title":"智能合约语言 Solidity 教程系列5 - 数组介绍","slug":"solidity-arrays","date":"2018-03-12T16:00:00.000Z","updated":"2022-10-19T14:40:00.265Z","comments":null,"top":null,"path":"api/articles/solidity-arrays.json","realPath":"/2018/solidity-arrays/solidity-arrays/","excerpt":null,"keywords":"南山结庐,东篱先生","cover":null,"content":null,"raw":null,"categories":[{"name":"学习记录","path":"api/categories/学习记录.json"},{"name":"区块链","path":"api/categories/区块链.json"},{"name":"以太坊","path":"api/categories/以太坊.json"}],"tags":[{"name":"Solidity手册","path":"api/tags/Solidity手册.json"}]},{"title":"智能合约语言 Solidity 教程系列9 - 错误处理","slug":"solidity-errorhandler","date":"2018-04-08T07:58:00.000Z","updated":"2022-10-19T14:40:00.266Z","comments":null,"top":null,"path":"api/articles/solidity-errorhandler.json","realPath":"/2018/solidity-errorhandler/index/","excerpt":null,"keywords":"南山结庐,东篱先生","cover":"/img/solidity_error1.jpg","content":null,"raw":null,"categories":[{"name":"学习记录","path":"api/categories/学习记录.json"},{"name":"区块链","path":"api/categories/区块链.json"},{"name":"以太坊","path":"api/categories/以太坊.json"}],"tags":[{"name":"Solidity手册","path":"api/tags/Solidity手册.json"}]},{"title":"智能合约语言 Solidity 教程系列10 - 完全理解函数修改器","slug":"solidity-modify","date":"2018-04-08T16:00:00.000Z","updated":"2022-10-19T14:40:00.266Z","comments":null,"top":null,"path":"api/articles/solidity-modify.json","realPath":"/2018/solidity-modify/index/","excerpt":null,"keywords":"南山结庐,东篱先生","cover":null,"content":null,"raw":null,"categories":[{"name":"学习记录","path":"api/categories/学习记录.json"},{"name":"区块链","path":"api/categories/区块链.json"},{"name":"以太坊","path":"api/categories/以太坊.json"}],"tags":[{"name":"Solidity手册","path":"api/tags/Solidity手册.json"}]},{"title":"智能合约语言 Solidity 教程系列6 - 结构体与映射","slug":"solidity-structs","date":"2018-03-13T05:50:23.000Z","updated":"2022-10-19T14:40:00.267Z","comments":null,"top":null,"path":"api/articles/solidity-structs.json","realPath":"/2018/solidity-structs/solidity-structs/","excerpt":null,"keywords":"南山结庐,东篱先生","cover":null,"content":null,"raw":null,"categories":[{"name":"学习记录","path":"api/categories/学习记录.json"},{"name":"区块链","path":"api/categories/区块链.json"},{"name":"以太坊","path":"api/categories/以太坊.json"}],"tags":[{"name":"Solidity手册","path":"api/tags/Solidity手册.json"}]},{"title":"智能合约语言 Solidity 教程系列7 - 以太单位及时间单位","slug":"solidity-unit","date":"2018-03-14T16:00:00.000Z","updated":"2022-10-19T14:40:00.267Z","comments":null,"top":null,"path":"api/articles/solidity-unit.json","realPath":"/2018/solidity-unit/solidity-unit/","excerpt":null,"keywords":"南山结庐,东篱先生","cover":null,"content":null,"raw":null,"categories":[{"name":"学习记录","path":"api/categories/学习记录.json"},{"name":"区块链","path":"api/categories/区块链.json"},{"name":"以太坊","path":"api/categories/以太坊.json"}],"tags":[{"name":"Solidity手册","path":"api/tags/Solidity手册.json"}]},{"title":"智能合约语言 Solidity 教程系列1 - 类型介绍","slug":"solidity1","date":"2018-02-28T16:00:00.000Z","updated":"2022-10-19T14:40:00.268Z","comments":null,"top":null,"path":"api/articles/solidity1.json","realPath":"/2018/solidity1/index/","excerpt":null,"keywords":"南山结庐,东篱先生","cover":null,"content":null,"raw":null,"categories":[{"name":"学习记录","path":"api/categories/学习记录.json"},{"name":"区块链","path":"api/categories/区块链.json"},{"name":"以太坊","path":"api/categories/以太坊.json"}],"tags":[{"name":"Solidity手册","path":"api/tags/Solidity手册.json"}]},{"title":"智能合约语言 Solidity 教程系列3 - 类型介绍","slug":"solidity_func","date":"2018-03-08T16:00:00.000Z","updated":"2022-10-19T14:40:00.268Z","comments":null,"top":null,"path":"api/articles/solidity_func.json","realPath":"/2018/solidity_func/index/","excerpt":null,"keywords":"南山结庐,东篱先生","cover":null,"content":null,"raw":null,"categories":[{"name":"学习记录","path":"api/categories/学习记录.json"},{"name":"区块链","path":"api/categories/区块链.json"},{"name":"以太坊","path":"api/categories/以太坊.json"}],"tags":[{"name":"Solidity手册","path":"api/tags/Solidity手册.json"}]},{"title":"智能合约语言 Solidity 教程系列2 - 类型介绍","slug":"solidity2","date":"2018-03-04T16:00:00.000Z","updated":"2022-10-19T14:40:00.268Z","comments":null,"top":null,"path":"api/articles/solidity2.json","realPath":"/2018/solidity2/index/","excerpt":null,"keywords":"南山结庐,东篱先生","cover":null,"content":null,"raw":null,"categories":[{"name":"学习记录","path":"api/categories/学习记录.json"},{"name":"区块链","path":"api/categories/区块链.json"},{"name":"以太坊","path":"api/categories/以太坊.json"}],"tags":[{"name":"Solidity手册","path":"api/tags/Solidity手册.json"}]},{"title":"智能合约语言 Solidity 教程系列4 - 数据存储位置分析","slug":"solidity_reftype_datalocation","date":"2018-03-11T16:00:00.000Z","updated":"2022-10-19T14:40:00.269Z","comments":null,"top":null,"path":"api/articles/solidity_reftype_datalocation.json","realPath":"/2018/solidity_reftype_datalocation/index/","excerpt":null,"keywords":"南山结庐,东篱先生","cover":null,"content":null,"raw":null,"categories":[{"name":"学习记录","path":"api/categories/学习记录.json"},{"name":"区块链","path":"api/categories/区块链.json"},{"name":"以太坊","path":"api/categories/以太坊.json"}],"tags":[{"name":"Solidity手册","path":"api/tags/Solidity手册.json"}]},{"title":"剖析非同质化代币ERC721-全面解析ERC721标准","slug":"token-erc721","date":"2018-03-23T04:02:22.000Z","updated":"2022-10-19T14:40:00.272Z","comments":null,"top":null,"path":"api/articles/token-erc721.json","realPath":"/2018/token-erc721/index/","excerpt":null,"keywords":"南山结庐,东篱先生","cover":null,"content":null,"raw":null,"categories":[{"name":"学习记录","path":"api/categories/学习记录.json"},{"name":"区块链","path":"api/categories/区块链.json"},{"name":"以太坊","path":"api/categories/以太坊.json"}],"tags":[{"name":"区块链","path":"api/tags/区块链.json"},{"name":"以太坊","path":"api/tags/以太坊.json"},{"name":"ERC721","path":"api/tags/ERC721.json"}]},{"title":"以太坊是什么 - 以太坊开发入门指南","slug":"whatiseth","date":"2018-02-22T05:02:22.000Z","updated":"2022-10-19T14:40:00.274Z","comments":null,"top":null,"path":"api/articles/whatiseth.json","realPath":"/2018/whatiseth/index/","excerpt":null,"keywords":"南山结庐,东篱先生","cover":null,"content":null,"raw":null,"categories":[{"name":"学习记录","path":"api/categories/学习记录.json"},{"name":"区块链","path":"api/categories/区块链.json"},{"name":"以太坊","path":"api/categories/以太坊.json"}],"tags":[{"name":"ethereum","path":"api/tags/ethereum.json"},{"name":"以太坊概念","path":"api/tags/以太坊概念.json"},{"name":"以太坊入门","path":"api/tags/以太坊入门.json"}]}]}